SecureZip/__init__.py
SecureZip-0.0.2.dist-info/LICENSE
SecureZip-0.0.2.dist-info/METADATA
SecureZip-0.0.2.dist-info/WHEEL
SecureZip-0.0.2.dist-info/top_level.txt
SecureZip-0.0.2.dist-info/RECORD
