Metadata-Version: 2.1
Name: SecureZip
Version: 0.0.2
Summary: Gathers information on a zip, mainly for seeing wether the zip could be considered malicious (Zipbomb, travelsal etc.). Work in progress.
Home-page: https://github.com/kuviokelluja/SecureZip
Author: Tony Rintala
Author-email: rintala.tony@gmail.com
License: MIT
Platform: UNKNOWN
Requires-Dist: psutil
